data_contract_validator/__init__.py
data_contract_validator/cli.py
data_contract_validator/py.typed
data_contract_validator/core/__init__.py
data_contract_validator/core/models.py
data_contract_validator/core/validator.py
data_contract_validator/extractors/__init__.py
data_contract_validator/extractors/base.py
data_contract_validator/extractors/dbt.py
data_contract_validator/extractors/fastapi.py
data_contract_validator/integrations/__init__.py
data_contract_validator/templates/github-actions-template.yml
data_contract_validator-1.0.5.dist-info/licenses/LICENSE
data_contract_validator-1.0.5.dist-info/METADATA
data_contract_validator-1.0.5.dist-info/WHEEL
data_contract_validator-1.0.5.dist-info/entry_points.txt
data_contract_validator-1.0.5.dist-info/top_level.txt
data_contract_validator-1.0.5.dist-info/RECORD
