Metadata-Version: 2.4
Name: data-contract-validator
Version: 1.0.5
Summary: Critical bug fixes: DBT extractor return paths, function signatures, error handling, and GitHub API rate limiting
Author-email: Ogunniran Siji <ogunniransiji@gmail.com>
Maintainer-email: Ogunniran Siji <ogunniransiji@gmail.com>
License: MIT
Project-URL: Homepage, https://github.com/OGsiji/data-contract-validator
Project-URL: Documentation, https://github.com/OGsiji/data-contract-validator/blob/main/README.md
Project-URL: Repository, https://github.com/OGsiji/data-contract-validator
Project-URL: Bug Reports, https://github.com/OGsiji/data-contract-validator/issues
Project-URL: Changelog, https://github.com/OGsiji/data-contract-validator/blob/main/CHANGELOG.md
Keywords: dbt,fastapi,contract-testing,api-validation,data-engineering,schema-validation,ci-cd,devops
Classifier: Development Status :: 4 - Beta
Classifier: Intended Audience :: Developers
Classifier: License :: OSI Approved :: MIT License
Classifier: Operating System :: OS Independent
Classifier: Programming Language :: Python :: 3
Classifier: Programming Language :: Python :: 3.8
Classifier: Programming Language :: Python :: 3.9
Classifier: Programming Language :: Python :: 3.10
Classifier: Programming Language :: Python :: 3.11
Classifier: Programming Language :: Python :: 3.12
Classifier: Topic :: Software Development :: Quality Assurance
Classifier: Topic :: Software Development :: Testing
Classifier: Topic :: Database
Classifier: Topic :: Internet :: WWW/HTTP :: HTTP Servers
Requires-Python: >=3.8
License-File: LICENSE
Requires-Dist: pydantic>=2.0.0
Requires-Dist: PyYAML>=6.0
Requires-Dist: requests>=2.25.0
Requires-Dist: click>=8.0.0
Provides-Extra: dev
Requires-Dist: pytest>=7.0.0; extra == "dev"
Requires-Dist: pytest-cov>=4.0.0; extra == "dev"
Requires-Dist: black>=22.0.0; extra == "dev"
Requires-Dist: flake8>=4.0.0; extra == "dev"
Requires-Dist: mypy>=0.991; extra == "dev"
Requires-Dist: pre-commit>=2.20.0; extra == "dev"
Requires-Dist: build>=0.8.0; extra == "dev"
Requires-Dist: twine>=4.0.0; extra == "dev"
Provides-Extra: test
Requires-Dist: pytest>=7.0.0; extra == "test"
Requires-Dist: pytest-cov>=4.0.0; extra == "test"
Requires-Dist: pytest-mock>=3.8.0; extra == "test"
Dynamic: license-file
